{"images/Cosplay1.jpg":["images/Cosplay1.jpg"],"images/Cosplay2.jpg":["images/Cosplay2.jpg"],"images/Cosplay3.jpg":["images/Cosplay3.jpg"],"images/Cosplay4.jpg":["images/Cosplay4.jpg"],"images/Cosplay5.jpg":["images/Cosplay5.jpg"],"images/Cosplay6.jpg":["images/Cosplay6.jpg"],"images/all.jpg":["images/all.jpg"],"images/beauty.jpg":["images/beauty.jpg"],"images/beauty1.jpg":["images/beauty1.jpg"],"images/beauty2.jpg":["images/beauty2.jpg"],"images/beauty3.jpg":["images/beauty3.jpg"],"images/beauty4.jpg":["images/beauty4.jpg"],"images/icon.png":["images/icon.png"],"images/image1.png":["images/image1.png"],"images/images.rar":["images/images.rar"],"images/man1.jpg":["images/man1.jpg"],"images/man2.jpg":["images/man2.jpg"],"images/man3.jpg":["images/man3.jpg"],"images/man4.jpg":["images/man4.jpg"],"images/national1.jpg":["images/national1.jpg"],"images/national2.jpg":["images/national2.jpg"],"images/national3.png":["images/national3.png"],"images/national4.png":["images/national4.png"],"images/profile3.jpg":["images/profile3.jpg"],"images/profile4.jpg":["images/profile4.jpg"],"images/profile5.jpg":["images/profile5.jpg"],"images/shoes.png":["images/shoes.png"],"images/slider.png":["images/slider.png"],"images/slider1.png":["images/slider1.png"],"images/slider2.png":["images/slider2.png"],"packages/cupertino_icons/assets/CupertinoIcons.ttf":["packages/cupertino_icons/assets/CupertinoIcons.ttf"]}